odoo/addons/autovacuum_message_attachment/README.rst
odoo/addons/autovacuum_message_attachment/__init__.py
odoo/addons/autovacuum_message_attachment/__manifest__.py
odoo/addons/autovacuum_message_attachment/data/data.xml
odoo/addons/autovacuum_message_attachment/i18n/autovacuum_mail_message.pot
odoo/addons/autovacuum_message_attachment/i18n/autovacuum_message_attachment.pot
odoo/addons/autovacuum_message_attachment/i18n/fr.po
odoo/addons/autovacuum_message_attachment/models/__init__.py
odoo/addons/autovacuum_message_attachment/models/autovacuum_mixin.py
odoo/addons/autovacuum_message_attachment/models/base.py
odoo/addons/autovacuum_message_attachment/models/ir_attachment.py
odoo/addons/autovacuum_message_attachment/models/mail_message.py
odoo/addons/autovacuum_message_attachment/models/vacuum_rule.py
odoo/addons/autovacuum_message_attachment/readme/CONFIGURE.rst
odoo/addons/autovacuum_message_attachment/readme/CONTRIBUTORS.rst
odoo/addons/autovacuum_message_attachment/readme/DESCRIPTION.rst
odoo/addons/autovacuum_message_attachment/readme/ROADMAP.rst
odoo/addons/autovacuum_message_attachment/security/ir.model.access.csv
odoo/addons/autovacuum_message_attachment/static/description/icon.png
odoo/addons/autovacuum_message_attachment/static/description/index.html
odoo/addons/autovacuum_message_attachment/tests/__init__.py
odoo/addons/autovacuum_message_attachment/tests/test_vacuum_rule.py
odoo/addons/autovacuum_message_attachment/views/rule_vacuum.xml
odoo12_addon_autovacuum_message_attachment-12.0.1.1.1.dist-info/METADATA
odoo12_addon_autovacuum_message_attachment-12.0.1.1.1.dist-info/WHEEL
odoo12_addon_autovacuum_message_attachment-12.0.1.1.1.dist-info/top_level.txt
odoo12_addon_autovacuum_message_attachment-12.0.1.1.1.dist-info/RECORD
